mly_pipeline/__init__.py
mly_pipeline/_version.py
mly_pipeline/continuous_FAR.py
mly_pipeline/continuous_FAR_test.py
mly_pipeline/create_status_page.py
mly_pipeline/initialization.py
mly_pipeline/make_eff_estimation.py
mly_pipeline/manager.py
mly_pipeline/mly_to_grace.py
mly_pipeline/offline_search.py
mly_pipeline/search.py
mly_pipeline/search_functions.py
mly_pipeline/tests/__init__.py
mly_pipeline/tests/test_skymap_generation.py
mly_pipeline-1.1.2.dist-info/LICENSE
mly_pipeline-1.1.2.dist-info/METADATA
mly_pipeline-1.1.2.dist-info/WHEEL
mly_pipeline-1.1.2.dist-info/entry_points.txt
mly_pipeline-1.1.2.dist-info/top_level.txt
mly_pipeline-1.1.2.dist-info/RECORD
