Metadata-Version: 2.1
Name: mly_pipeline
Version: 1.1.2
Summary: Search pipeline to run online and offline GW searches with mly package.
Author-email: Vasileios SKliris <sklirisv@cardiff.ac.uk>
Keywords: ml,gravitational waves,bursts
Classifier: Programming Language :: Python :: 3
Requires-Python: >=3.7
License-File: LICENSE
Requires-Dist: mly
Requires-Dist: spython==0.2
Requires-Dist: hermes.aeriel
Requires-Dist: hermes.quiver
Requires-Dist: hermes.stillwater
